MANIFEST.in
README.txt
setup.cfg
setup.py
docs/HISTORY.txt
examples/basic1.py
examples/basic1.xml
examples/basic2.py
examples/basic2.xml
pyjon/__init__.py
pyjon.reports.egg-info/PKG-INFO
pyjon.reports.egg-info/SOURCES.txt
pyjon.reports.egg-info/dependency_links.txt
pyjon.reports.egg-info/entry_points.txt
pyjon.reports.egg-info/namespace_packages.txt
pyjon.reports.egg-info/not-zip-safe
pyjon.reports.egg-info/requires.txt
pyjon.reports.egg-info/top_level.txt
pyjon/reports/__init__.py
pyjon/reports/factory.py
pyjon/reports/template.py