Metadata-Version: 1.0
Name: pyjon.reports
Version: 0.5
Summary: This is a reporting bird.
Home-page: UNKNOWN
Author: Jonathan Schemoul, Jerome Collette
Author-email: jonathan.schemoul@gmail.com, collette.jerome@gmail.com
License: MIT
Keywords: pdf template report rml splitting
Platform: UNKNOWN
Classifier: Programming Language :: Python
Classifier: Topic :: Software Development :: Libraries :: Python Modules
